passagemath_m4ri_m4rie/__init__.py
passagemath_m4ri_m4rie-10.6.47.dist-info/DELVEWHEEL
passagemath_m4ri_m4rie-10.6.47.dist-info/METADATA
passagemath_m4ri_m4rie-10.6.47.dist-info/RECORD
passagemath_m4ri_m4rie-10.6.47.dist-info/top_level.txt
passagemath_m4ri_m4rie-10.6.47.dist-info/WHEEL
passagemath_m4ri_m4rie.libs/libgd-3-21d31afc79055cb4eb8e42ee0a2882b8.dll
passagemath_m4ri_m4rie.libs/libgmp-10-6a8fe126122672a8aed2558e30454e74.dll
passagemath_m4ri_m4rie.libs/libiconv-2-ff31fa811f9c07cc7fdaa68c9e8bca3a.dll
passagemath_m4ri_m4rie.libs/libm4ri-1-6c3a7f7edc8729450f1b67cb7a133e38.dll
passagemath_m4ri_m4rie.libs/libm4rie-1-84126caa1f0befda05f09e3a291700f0.dll
passagemath_m4ri_m4rie.libs/libpng16-16-cb8c14eb5051bd4d151a2cf6508e45b2.dll
passagemath_m4ri_m4rie.libs/zlib1-1a487c70e6c5cd27981d0ea3438a0ba6.dll
sage/all__sagemath_m4ri_m4rie.py
sage/libs/all__sagemath_m4ri_m4rie.py
sage/libs/m4ri.pxd
sage/libs/m4rie.pxd
sage/matrix/all__sagemath_m4ri_m4rie.py
sage/matrix/matrix_gf2e_dense.cp314-win_amd64.pyd
sage/matrix/matrix_gf2e_dense.pxd
sage/matrix/matrix_gf2e_dense.pyx
sage/matrix/matrix_mod2_dense.cp314-win_amd64.pyd
sage/matrix/matrix_mod2_dense.pxd
sage/matrix/matrix_mod2_dense.pyx
sage/modules/all__sagemath_m4ri_m4rie.py
sage/modules/numpy_util.cp314-win_amd64.pyd
sage/modules/numpy_util.pxd
sage/modules/numpy_util.pyx
sage/modules/vector_mod2_dense.cp314-win_amd64.pyd
sage/modules/vector_mod2_dense.pxd
sage/modules/vector_mod2_dense.pyx
